omophub/__init__.py
omophub/_client.py
omophub/_config.py
omophub/_exceptions.py
omophub/_http.py
omophub/_pagination.py
omophub/_request.py
omophub/_types.py
omophub/_version.py
omophub/resources/__init__.py
omophub/resources/concepts.py
omophub/resources/domains.py
omophub/resources/hierarchy.py
omophub/resources/mappings.py
omophub/resources/relationships.py
omophub/resources/search.py
omophub/resources/vocabularies.py
omophub/types/__init__.py
omophub/types/common.py
omophub/types/concept.py
omophub/types/domain.py
omophub/types/hierarchy.py
omophub/types/mapping.py
omophub/types/relationship.py
omophub/types/search.py
omophub/types/vocabulary.py
omophub-1.3.1.dist-info/METADATA
omophub-1.3.1.dist-info/WHEEL
omophub-1.3.1.dist-info/licenses/LICENSE
omophub-1.3.1.dist-info/RECORD
