Metadata-Version: 2.4
Name: omophub
Version: 1.3.1
Summary: Python SDK for OMOPHub - Medical Vocabulary API
Project-URL: Homepage, https://omophub.com
Project-URL: Documentation, https://docs.omophub.com/use-with-python
Project-URL: Repository, https://github.com/omopHub/omophub-python
Project-URL: Changelog, https://github.com/omopHub/omophub-python/blob/main/CHANGELOG.md
Project-URL: Issues, https://github.com/omopHub/omophub-python/issues
Author-email: OMOPHub <sdk@omophub.com>
License-Expression: MIT
License-File: LICENSE
Keywords: api,athena,clinical,healthcare,icd10,loinc,medical,ohdsi,omop,rxnorm,sdk,snomed,terminology,vocabulary
Classifier: Development Status :: 4 - Beta
Classifier: Intended Audience :: Developers
Classifier: Intended Audience :: Healthcare Industry
Classifier: Intended Audience :: Science/Research
Classifier: License :: OSI Approved :: MIT License
Classifier: Operating System :: OS Independent
Classifier: Programming Language :: Python :: 3
Classifier: Programming Language :: Python :: 3.10
Classifier: Programming Language :: Python :: 3.11
Classifier: Programming Language :: Python :: 3.12
Classifier: Programming Language :: Python :: 3.13
Classifier: Topic :: Scientific/Engineering :: Medical Science Apps.
Classifier: Topic :: Software Development :: Libraries :: Python Modules
Classifier: Typing :: Typed
Requires-Python: >=3.10
Requires-Dist: httpx>=0.27.0
Requires-Dist: typing-extensions>=4.5.0
Provides-Extra: dev
Requires-Dist: mypy>=1.8.0; extra == 'dev'
Requires-Dist: pytest-asyncio>=0.23.0; extra == 'dev'
Requires-Dist: pytest-cov>=4.1.0; extra == 'dev'
Requires-Dist: pytest>=8.0.0; extra == 'dev'
Requires-Dist: python-dotenv>=1.0.0; extra == 'dev'
Requires-Dist: respx>=0.21.0; extra == 'dev'
Requires-Dist: ruff>=0.3.0; extra == 'dev'
